{"cameraMode":{"drawMode":0,"name":"Shaded","section":"Shading Mode"},"sceneLighting":true,"audioPlay":false,"sceneViewState":{"m_AlwaysRefresh":false,"showFog":true,"showSkybox":true,"showFlares":true,"showImageEffects":true,"showParticleSystems":true,"showVisualEffectGraphs":true,"m_FxEnabled":true},"in2DMode":false,"pivot":{"x":584.0,"y":328.5,"z":0.0},"rotation":{"x":-0.0459931381046772,"y":0.7677809596061707,"z":-0.05531155690550804,"w":-0.636664092540741},"size":463.59075927734377,"orthographic":true}