{"cameraMode":{"drawMode":0,"name":"Shaded","section":"Shading Mode"},"sceneLighting":true,"audioPlay":false,"sceneViewState":{"m_AlwaysRefresh":false,"showFog":true,"showSkybox":true,"showFlares":true,"showImageEffects":true,"showParticleSystems":true,"showVisualEffectGraphs":true,"m_FxEnabled":true},"in2DMode":false,"pivot":{"x":750.0,"y":5.473278045654297,"z":750.0},"rotation":{"x":-0.2348201721906662,"y":0.34027913212776186,"z":-0.0880674496293068,"w":-0.9062539339065552},"size":89.67484283447266,"orthographic":true}